tsp_solver_jtw/example_usage.py
tsp_solver_jtw/utils.py
tsp_solver_jtw/algorithms/Asearch.py
tsp_solver_jtw/algorithms/hill_climbing.py
tsp_solver_jtw/algorithms/random_search.py
tsp_solver_jtw/algorithms/simulated_annealing.py
jw96-0.1.0.dist-info/METADATA
jw96-0.1.0.dist-info/WHEEL
jw96-0.1.0.dist-info/top_level.txt
jw96-0.1.0.dist-info/RECORD
